


Both the cyclic and acyclic graphs of the bytecode of method \texttt{isMember} at Fig.~\ref{isMemBC} is at Fig. ~\ref{blockBC}. Blocks are represented by boxes. Black arrows stand for relation $\execRel^A$. Dashed arrows stand for the acyclic relation $\execRel$.





\begin{figure}[p]
\begin{center}
\begin{tabular}{rl}
 1 iconst_0
 2 istore_3 
 3 iconst_0 
 4 istore_3 
 5 goto 29 
 6 aload_0
 7 getfield #19 <test/ListArray.list> 
 8 iload_3 
 9 aaload 
10 aload_1 
11 if_acmpne 26
12 aload_0 
13 getfield #19 <test/ListArray.list>
14 iload_3 
15 aload_2 
16 aastore 
17 iconst_1 
18 ireturn 
19 iinc 3 by 1 
20 iload_3 
21 aload_0 
22 getfield #19 <test/ListArray.list> 
23 arraylength  
24 if_icmplt 7  
25 iconst_0  
26 ireturn  
\end{tabular}
\end{center}
\caption{the bytecode of method \texttt{isMember}}
\label{isMemBC}
\end{figure}

